<?xml version="1.0" encoding="utf-8"?>
<StructureDefinition xmlns="http://hl7.org/fhir">
  <id value="25868b7e-c887-422c-a131-84c1a4b4e854" />
  <meta>
    <versionId value="2" />
    <lastUpdated value="2017-10-30T12:33:29.104+01:00" />
  </meta>
  <extension url="http://hl7.org/fhir/StructureDefinition/structuredefinition-wg">
    <valueCode value="pc" />
  </extension>
  <url value="http://www.csc.com/PublicServices/HC/FHIR/Profiles/DXC_HC_Procedure" />
  <version value="1" />
  <name value="DXC_HC_Procedure" />
  <status value="draft" />
  <date value="2017-05-25T13:17:12.557747+02:00" />
  <fhirVersion value="4.0.0" />
  <kind value="resource" />
  <abstract value="false" />
  <type value="Procedure" />
  <baseDefinition value="http://hl7.org/fhir/StructureDefinition/Procedure" />
  <derivation value="constraint" />
  <differential>
    <element id="Procedure.id">
      <path value="Procedure.id" />
      <min value="1" />
    </element>
    <element id="Procedure.meta">
      <extension url="http://hl7.org/fhir/StructureDefinition/structuredefinition-standards-status">
        <valueCode value="normative" />
      </extension>
      <extension url="http://hl7.org/fhir/StructureDefinition/structuredefinition-normative-version">
        <valueCode value="4.0.0" />
      </extension>
      <path value="Procedure.meta" />
      <max value="0" />
    </element>
    <element id="Procedure.implicitRules">
      <extension url="http://hl7.org/fhir/StructureDefinition/structuredefinition-standards-status">
        <valueCode value="normative" />
      </extension>
      <extension url="http://hl7.org/fhir/StructureDefinition/structuredefinition-normative-version">
        <valueCode value="4.0.0" />
      </extension>
      <path value="Procedure.implicitRules" />
      <max value="0" />
    </element>
    <element id="Procedure.language">
      <extension url="http://hl7.org/fhir/StructureDefinition/structuredefinition-standards-status">
        <valueCode value="normative" />
      </extension>
      <extension url="http://hl7.org/fhir/StructureDefinition/structuredefinition-normative-version">
        <valueCode value="4.0.0" />
      </extension>
      <path value="Procedure.language" />
      <max value="0" />
    </element>
    <element id="Procedure.contained">
      <path value="Procedure.contained" />
      <max value="0" />
    </element>
    <element id="Procedure.identifier">
      <extension url="http://hl7.org/fhir/StructureDefinition/structuredefinition-standards-status">
        <valueCode value="normative" />
      </extension>
      <extension url="http://hl7.org/fhir/StructureDefinition/structuredefinition-normative-version">
        <valueCode value="4.0.0" />
      </extension>
      <path value="Procedure.identifier" />
      <max value="0" />
    </element>
    <element id="Procedure.instantiatesCanonical">
      <extension url="http://hl7.org/fhir/StructureDefinition/structuredefinition-standards-status">
        <valueCode value="normative" />
      </extension>
      <extension url="http://hl7.org/fhir/StructureDefinition/structuredefinition-normative-version">
        <valueCode value="4.0.0" />
      </extension>
      <path value="Procedure.instantiatesCanonical" />
      <max value="0" />
    </element>
    <element id="Procedure.instantiatesUri">
      <extension url="http://hl7.org/fhir/StructureDefinition/structuredefinition-standards-status">
        <valueCode value="normative" />
      </extension>
      <extension url="http://hl7.org/fhir/StructureDefinition/structuredefinition-normative-version">
        <valueCode value="4.0.0" />
      </extension>
      <path value="Procedure.instantiatesUri" />
      <max value="0" />
    </element>
    <element id="Procedure.basedOn">
      <extension url="http://hl7.org/fhir/StructureDefinition/structuredefinition-standards-status">
        <valueCode value="normative" />
      </extension>
      <extension url="http://hl7.org/fhir/StructureDefinition/structuredefinition-normative-version">
        <valueCode value="4.0.0" />
      </extension>
      <path value="Procedure.basedOn" />
      <max value="1" />
      <type>
        <code value="Reference" />
        <targetProfile value="http://hl7.org/fhir/StructureDefinition/ServiceRequest" />
      </type>
      <type>
        <code value="Reference" />
        <targetProfile value="http://hl7.org/fhir/StructureDefinition/NutritionOrder" />
      </type>
    </element>
    <element id="Procedure.partOf">
      <extension url="http://hl7.org/fhir/StructureDefinition/structuredefinition-standards-status">
        <valueCode value="normative" />
      </extension>
      <extension url="http://hl7.org/fhir/StructureDefinition/structuredefinition-normative-version">
        <valueCode value="4.0.0" />
      </extension>
      <path value="Procedure.partOf" />
      <max value="0" />
    </element>
    <element id="Procedure.statusReason.id">
      <path value="Procedure.statusReason.id" />
      <max value="0" />
    </element>
    <element id="Procedure.statusReason.coding">
      <extension url="http://hl7.org/fhir/StructureDefinition/structuredefinition-standards-status">
        <valueCode value="normative" />
      </extension>
      <extension url="http://hl7.org/fhir/StructureDefinition/structuredefinition-normative-version">
        <valueCode value="4.0.0" />
      </extension>
      <path value="Procedure.statusReason.coding" />
      <min value="1" />
    </element>
    <element id="Procedure.statusReason.coding.id">
      <path value="Procedure.statusReason.coding.id" />
      <max value="0" />
    </element>
    <element id="Procedure.statusReason.coding.system">
      <extension url="http://hl7.org/fhir/StructureDefinition/structuredefinition-standards-status">
        <valueCode value="normative" />
      </extension>
      <extension url="http://hl7.org/fhir/StructureDefinition/structuredefinition-normative-version">
        <valueCode value="4.0.0" />
      </extension>
      <path value="Procedure.statusReason.coding.system" />
      <max value="0" />
    </element>
    <element id="Procedure.statusReason.coding.version">
      <extension url="http://hl7.org/fhir/StructureDefinition/structuredefinition-standards-status">
        <valueCode value="normative" />
      </extension>
      <extension url="http://hl7.org/fhir/StructureDefinition/structuredefinition-normative-version">
        <valueCode value="4.0.0" />
      </extension>
      <path value="Procedure.statusReason.coding.version" />
      <max value="0" />
    </element>
    <element id="Procedure.statusReason.coding.code">
      <extension url="http://hl7.org/fhir/StructureDefinition/structuredefinition-standards-status">
        <valueCode value="normative" />
      </extension>
      <extension url="http://hl7.org/fhir/StructureDefinition/structuredefinition-normative-version">
        <valueCode value="4.0.0" />
      </extension>
      <path value="Procedure.statusReason.coding.code" />
      <min value="1" />
    </element>
    <element id="Procedure.statusReason.coding.display">
      <extension url="http://hl7.org/fhir/StructureDefinition/structuredefinition-standards-status">
        <valueCode value="normative" />
      </extension>
      <extension url="http://hl7.org/fhir/StructureDefinition/structuredefinition-normative-version">
        <valueCode value="4.0.0" />
      </extension>
      <extension url="http://hl7.org/fhir/StructureDefinition/elementdefinition-translatable">
        <valueBoolean value="true" />
      </extension>
      <path value="Procedure.statusReason.coding.display" />
      <min value="1" />
    </element>
    <element id="Procedure.statusReason.coding.userSelected">
      <extension url="http://hl7.org/fhir/StructureDefinition/structuredefinition-standards-status">
        <valueCode value="normative" />
      </extension>
      <extension url="http://hl7.org/fhir/StructureDefinition/structuredefinition-normative-version">
        <valueCode value="4.0.0" />
      </extension>
      <path value="Procedure.statusReason.coding.userSelected" />
      <max value="0" />
    </element>
    <element id="Procedure.statusReason.text">
      <extension url="http://hl7.org/fhir/StructureDefinition/structuredefinition-standards-status">
        <valueCode value="normative" />
      </extension>
      <extension url="http://hl7.org/fhir/StructureDefinition/structuredefinition-normative-version">
        <valueCode value="4.0.0" />
      </extension>
      <extension url="http://hl7.org/fhir/StructureDefinition/elementdefinition-translatable">
        <valueBoolean value="true" />
      </extension>
      <path value="Procedure.statusReason.text" />
      <max value="0" />
    </element>
    <element id="Procedure.category">
      <extension url="http://hl7.org/fhir/StructureDefinition/structuredefinition-standards-status">
        <valueCode value="normative" />
      </extension>
      <extension url="http://hl7.org/fhir/StructureDefinition/structuredefinition-normative-version">
        <valueCode value="4.0.0" />
      </extension>
      <path value="Procedure.category" />
      <max value="0" />
    </element>
    <element id="Procedure.code">
      <extension url="http://hl7.org/fhir/StructureDefinition/structuredefinition-standards-status">
        <valueCode value="normative" />
      </extension>
      <extension url="http://hl7.org/fhir/StructureDefinition/structuredefinition-normative-version">
        <valueCode value="4.0.0" />
      </extension>
      <path value="Procedure.code" />
      <min value="1" />
    </element>
    <element id="Procedure.code.id">
      <path value="Procedure.code.id" />
      <max value="0" />
    </element>
    <element id="Procedure.code.coding">
      <extension url="http://hl7.org/fhir/StructureDefinition/structuredefinition-standards-status">
        <valueCode value="normative" />
      </extension>
      <extension url="http://hl7.org/fhir/StructureDefinition/structuredefinition-normative-version">
        <valueCode value="4.0.0" />
      </extension>
      <path value="Procedure.code.coding" />
      <min value="1" />
    </element>
    <element id="Procedure.code.coding.id">
      <path value="Procedure.code.coding.id" />
      <max value="0" />
    </element>
    <element id="Procedure.code.coding.version">
      <extension url="http://hl7.org/fhir/StructureDefinition/structuredefinition-standards-status">
        <valueCode value="normative" />
      </extension>
      <extension url="http://hl7.org/fhir/StructureDefinition/structuredefinition-normative-version">
        <valueCode value="4.0.0" />
      </extension>
      <path value="Procedure.code.coding.version" />
      <max value="0" />
    </element>
    <element id="Procedure.code.coding.code">
      <extension url="http://hl7.org/fhir/StructureDefinition/structuredefinition-standards-status">
        <valueCode value="normative" />
      </extension>
      <extension url="http://hl7.org/fhir/StructureDefinition/structuredefinition-normative-version">
        <valueCode value="4.0.0" />
      </extension>
      <path value="Procedure.code.coding.code" />
      <min value="1" />
    </element>
    <element id="Procedure.code.coding.userSelected">
      <extension url="http://hl7.org/fhir/StructureDefinition/structuredefinition-standards-status">
        <valueCode value="normative" />
      </extension>
      <extension url="http://hl7.org/fhir/StructureDefinition/structuredefinition-normative-version">
        <valueCode value="4.0.0" />
      </extension>
      <path value="Procedure.code.coding.userSelected" />
      <max value="0" />
    </element>
    <element id="Procedure.code.text">
      <extension url="http://hl7.org/fhir/StructureDefinition/structuredefinition-standards-status">
        <valueCode value="normative" />
      </extension>
      <extension url="http://hl7.org/fhir/StructureDefinition/structuredefinition-normative-version">
        <valueCode value="4.0.0" />
      </extension>
      <extension url="http://hl7.org/fhir/StructureDefinition/elementdefinition-translatable">
        <valueBoolean value="true" />
      </extension>
      <path value="Procedure.code.text" />
      <max value="0" />
    </element>
    <element id="Procedure.subject">
      <extension url="http://hl7.org/fhir/StructureDefinition/structuredefinition-standards-status">
        <valueCode value="normative" />
      </extension>
      <extension url="http://hl7.org/fhir/StructureDefinition/structuredefinition-normative-version">
        <valueCode value="4.0.0" />
      </extension>
      <path value="Procedure.subject" />
      <min value="0" />
      <type>
        <code value="Reference" />
        <profile value="DXC_HC_Patient" />
        <targetProfile value="http://www.csc.com/PublicServices/HC/FHIR/Profiles/DXC_HC_Patient" />
      </type>
    </element>
    <element id="Procedure.subject.id">
      <path value="Procedure.subject.id" />
      <max value="0" />
    </element>
    <element id="Procedure.subject.reference">
      <extension url="http://hl7.org/fhir/StructureDefinition/structuredefinition-standards-status">
        <valueCode value="normative" />
      </extension>
      <extension url="http://hl7.org/fhir/StructureDefinition/structuredefinition-normative-version">
        <valueCode value="4.0.0" />
      </extension>
      <path value="Procedure.subject.reference" />
      <min value="1" />
    </element>
    <element id="Procedure.subject.identifier">
      <extension url="http://hl7.org/fhir/StructureDefinition/structuredefinition-standards-status">
        <valueCode value="normative" />
      </extension>
      <extension url="http://hl7.org/fhir/StructureDefinition/structuredefinition-normative-version">
        <valueCode value="4.0.0" />
      </extension>
      <path value="Procedure.subject.identifier" />
      <max value="0" />
    </element>
    <element id="Procedure.performed[x]">
      <extension url="http://hl7.org/fhir/StructureDefinition/structuredefinition-standards-status">
        <valueCode value="normative" />
      </extension>
      <extension url="http://hl7.org/fhir/StructureDefinition/structuredefinition-normative-version">
        <valueCode value="4.0.0" />
      </extension>
      <path value="Procedure.performed[x]" />
      <slicing>
        <discriminator>
          <type value="type" />
          <path value="$this" />
        </discriminator>
      </slicing>
      <min value="1" />
      <type>
        <code value="dateTime" />
      </type>
    </element>
    <element id="Procedure.performed[x]:performedDateTime">
      <extension url="http://hl7.org/fhir/StructureDefinition/structuredefinition-standards-status">
        <valueCode value="normative" />
      </extension>
      <extension url="http://hl7.org/fhir/StructureDefinition/structuredefinition-normative-version">
        <valueCode value="4.0.0" />
      </extension>
      <path value="Procedure.performed[x]" />
      <sliceName value="performedDateTime" />
      <min value="1" />
      <type>
        <code value="dateTime" />
      </type>
    </element>
    <element id="Procedure.recorder">
      <extension url="http://hl7.org/fhir/StructureDefinition/structuredefinition-standards-status">
        <valueCode value="normative" />
      </extension>
      <extension url="http://hl7.org/fhir/StructureDefinition/structuredefinition-normative-version">
        <valueCode value="4.0.0" />
      </extension>
      <path value="Procedure.recorder" />
      <max value="0" />
    </element>
    <element id="Procedure.asserter">
      <extension url="http://hl7.org/fhir/StructureDefinition/structuredefinition-standards-status">
        <valueCode value="normative" />
      </extension>
      <extension url="http://hl7.org/fhir/StructureDefinition/structuredefinition-normative-version">
        <valueCode value="4.0.0" />
      </extension>
      <path value="Procedure.asserter" />
      <max value="0" />
    </element>
    <element id="Procedure.performer">
      <extension url="http://hl7.org/fhir/StructureDefinition/structuredefinition-standards-status">
        <valueCode value="normative" />
      </extension>
      <extension url="http://hl7.org/fhir/StructureDefinition/structuredefinition-normative-version">
        <valueCode value="4.0.0" />
      </extension>
      <path value="Procedure.performer" />
      <min value="1" />
      <max value="1" />
    </element>
    <element id="Procedure.performer.id">
      <path value="Procedure.performer.id" />
      <max value="0" />
    </element>
    <element id="Procedure.performer.function">
      <extension url="http://hl7.org/fhir/StructureDefinition/structuredefinition-standards-status">
        <valueCode value="normative" />
      </extension>
      <extension url="http://hl7.org/fhir/StructureDefinition/structuredefinition-normative-version">
        <valueCode value="4.0.0" />
      </extension>
      <path value="Procedure.performer.function" />
      <max value="0" />
    </element>
    <element id="Procedure.performer.actor.id">
      <path value="Procedure.performer.actor.id" />
      <max value="0" />
    </element>
    <element id="Procedure.performer.actor.reference">
      <extension url="http://hl7.org/fhir/StructureDefinition/structuredefinition-standards-status">
        <valueCode value="normative" />
      </extension>
      <extension url="http://hl7.org/fhir/StructureDefinition/structuredefinition-normative-version">
        <valueCode value="4.0.0" />
      </extension>
      <path value="Procedure.performer.actor.reference" />
      <min value="1" />
    </element>
    <element id="Procedure.performer.actor.identifier">
      <extension url="http://hl7.org/fhir/StructureDefinition/structuredefinition-standards-status">
        <valueCode value="normative" />
      </extension>
      <extension url="http://hl7.org/fhir/StructureDefinition/structuredefinition-normative-version">
        <valueCode value="4.0.0" />
      </extension>
      <path value="Procedure.performer.actor.identifier" />
      <max value="0" />
    </element>
    <element id="Procedure.performer.actor.display">
      <extension url="http://hl7.org/fhir/StructureDefinition/structuredefinition-standards-status">
        <valueCode value="normative" />
      </extension>
      <extension url="http://hl7.org/fhir/StructureDefinition/structuredefinition-normative-version">
        <valueCode value="4.0.0" />
      </extension>
      <extension url="http://hl7.org/fhir/StructureDefinition/elementdefinition-translatable">
        <valueBoolean value="true" />
      </extension>
      <path value="Procedure.performer.actor.display" />
      <max value="0" />
    </element>
    <element id="Procedure.performer.onBehalfOf">
      <extension url="http://hl7.org/fhir/StructureDefinition/structuredefinition-standards-status">
        <valueCode value="normative" />
      </extension>
      <extension url="http://hl7.org/fhir/StructureDefinition/structuredefinition-normative-version">
        <valueCode value="4.0.0" />
      </extension>
      <path value="Procedure.performer.onBehalfOf" />
      <max value="0" />
    </element>
    <element id="Procedure.performer.role">
      <path value="Procedure.performer.role" />
      <max value="0" />
    </element>
    <element id="Procedure.location">
      <extension url="http://hl7.org/fhir/StructureDefinition/structuredefinition-standards-status">
        <valueCode value="normative" />
      </extension>
      <extension url="http://hl7.org/fhir/StructureDefinition/structuredefinition-normative-version">
        <valueCode value="4.0.0" />
      </extension>
      <path value="Procedure.location" />
      <max value="0" />
    </element>
    <element id="Procedure.reasonCode">
      <extension url="http://hl7.org/fhir/StructureDefinition/structuredefinition-standards-status">
        <valueCode value="normative" />
      </extension>
      <extension url="http://hl7.org/fhir/StructureDefinition/structuredefinition-normative-version">
        <valueCode value="4.0.0" />
      </extension>
      <path value="Procedure.reasonCode" />
      <max value="0" />
    </element>
    <element id="Procedure.reasonReference">
      <extension url="http://hl7.org/fhir/StructureDefinition/structuredefinition-standards-status">
        <valueCode value="normative" />
      </extension>
      <extension url="http://hl7.org/fhir/StructureDefinition/structuredefinition-normative-version">
        <valueCode value="4.0.0" />
      </extension>
      <path value="Procedure.reasonReference" />
      <max value="0" />
    </element>
    <element id="Procedure.bodySite">
      <extension url="http://hl7.org/fhir/StructureDefinition/structuredefinition-standards-status">
        <valueCode value="normative" />
      </extension>
      <extension url="http://hl7.org/fhir/StructureDefinition/structuredefinition-normative-version">
        <valueCode value="4.0.0" />
      </extension>
      <path value="Procedure.bodySite" />
      <max value="0" />
    </element>
    <element id="Procedure.outcome">
      <extension url="http://hl7.org/fhir/StructureDefinition/structuredefinition-standards-status">
        <valueCode value="normative" />
      </extension>
      <extension url="http://hl7.org/fhir/StructureDefinition/structuredefinition-normative-version">
        <valueCode value="4.0.0" />
      </extension>
      <path value="Procedure.outcome" />
      <max value="0" />
    </element>
    <element id="Procedure.report">
      <extension url="http://hl7.org/fhir/StructureDefinition/structuredefinition-standards-status">
        <valueCode value="normative" />
      </extension>
      <extension url="http://hl7.org/fhir/StructureDefinition/structuredefinition-normative-version">
        <valueCode value="4.0.0" />
      </extension>
      <path value="Procedure.report" />
      <max value="0" />
    </element>
    <element id="Procedure.complication">
      <extension url="http://hl7.org/fhir/StructureDefinition/structuredefinition-standards-status">
        <valueCode value="normative" />
      </extension>
      <extension url="http://hl7.org/fhir/StructureDefinition/structuredefinition-normative-version">
        <valueCode value="4.0.0" />
      </extension>
      <path value="Procedure.complication" />
      <max value="0" />
    </element>
    <element id="Procedure.complicationDetail">
      <extension url="http://hl7.org/fhir/StructureDefinition/structuredefinition-standards-status">
        <valueCode value="normative" />
      </extension>
      <extension url="http://hl7.org/fhir/StructureDefinition/structuredefinition-normative-version">
        <valueCode value="4.0.0" />
      </extension>
      <path value="Procedure.complicationDetail" />
      <max value="0" />
    </element>
    <element id="Procedure.followUp">
      <extension url="http://hl7.org/fhir/StructureDefinition/structuredefinition-standards-status">
        <valueCode value="normative" />
      </extension>
      <extension url="http://hl7.org/fhir/StructureDefinition/structuredefinition-normative-version">
        <valueCode value="4.0.0" />
      </extension>
      <path value="Procedure.followUp" />
      <max value="0" />
    </element>
    <element id="Procedure.note.id">
      <path value="Procedure.note.id" />
      <max value="0" />
    </element>
    <element id="Procedure.note.author[x]">
      <extension url="http://hl7.org/fhir/StructureDefinition/structuredefinition-standards-status">
        <valueCode value="normative" />
      </extension>
      <extension url="http://hl7.org/fhir/StructureDefinition/structuredefinition-normative-version">
        <valueCode value="4.0.0" />
      </extension>
      <path value="Procedure.note.author[x]" />
      <max value="0" />
    </element>
    <element id="Procedure.note.time">
      <extension url="http://hl7.org/fhir/StructureDefinition/structuredefinition-standards-status">
        <valueCode value="normative" />
      </extension>
      <extension url="http://hl7.org/fhir/StructureDefinition/structuredefinition-normative-version">
        <valueCode value="4.0.0" />
      </extension>
      <path value="Procedure.note.time" />
      <max value="0" />
    </element>
    <element id="Procedure.focalDevice">
      <extension url="http://hl7.org/fhir/StructureDefinition/structuredefinition-standards-status">
        <valueCode value="normative" />
      </extension>
      <extension url="http://hl7.org/fhir/StructureDefinition/structuredefinition-normative-version">
        <valueCode value="4.0.0" />
      </extension>
      <path value="Procedure.focalDevice" />
      <max value="0" />
    </element>
    <element id="Procedure.usedReference">
      <extension url="http://hl7.org/fhir/StructureDefinition/structuredefinition-standards-status">
        <valueCode value="normative" />
      </extension>
      <extension url="http://hl7.org/fhir/StructureDefinition/structuredefinition-normative-version">
        <valueCode value="4.0.0" />
      </extension>
      <path value="Procedure.usedReference" />
      <max value="0" />
    </element>
    <element id="Procedure.usedCode">
      <extension url="http://hl7.org/fhir/StructureDefinition/structuredefinition-standards-status">
        <valueCode value="normative" />
      </extension>
      <extension url="http://hl7.org/fhir/StructureDefinition/structuredefinition-normative-version">
        <valueCode value="4.0.0" />
      </extension>
      <path value="Procedure.usedCode" />
      <max value="0" />
    </element>
  </differential>
</StructureDefinition>